airtouch3/__init__.py
airtouch3/airtouch3.py
airtouch3/constants.py
airtouch3/helper.py
airtouch3-0.9.dist-info/LICENSE
airtouch3-0.9.dist-info/METADATA
airtouch3-0.9.dist-info/WHEEL
airtouch3-0.9.dist-info/top_level.txt
airtouch3-0.9.dist-info/RECORD
