Metadata-Version: 2.1
Name: airtouch3
Version: 0.9
Summary: API for the monitoring and control of a HVAC unit branded Polyaire Airtouch 3 over a local network
Home-page: https://github.com/tonymyatt/airtouch3api
Author: Tony Myatt
Author-email: tony@myatt.com.au
License: UNKNOWN
Project-URL: Bug Tracker, https://github.com/tonymyatt/airtouch3api/issues
Platform: UNKNOWN
Classifier: Programming Language :: Python :: 3
Classifier: License :: OSI Approved :: MIT License
Classifier: Operating System :: OS Independent
Requires-Python: >=3.6
License-File: LICENSE
